MANIFEST.in
README
setup.py
lodstats/RDFStats.py
lodstats/__init__.py
lodstats/exceptions.py
lodstats.egg-info/PKG-INFO
lodstats.egg-info/SOURCES.txt
lodstats.egg-info/dependency_links.txt
lodstats.egg-info/requires.txt
lodstats.egg-info/top_level.txt
lodstats/rdf/22-rdf-syntax-ns.rdf
lodstats/rdf/owl.rdf
lodstats/rdf/rdf-schema.rdf
lodstats/stats/ClassHierarchy.py
lodstats/stats/Classes.py
lodstats/stats/CookieCounter.py
lodstats/stats/Datatypes.py
lodstats/stats/Languages.py
lodstats/stats/LimitedSizeDict.py
lodstats/stats/Links.py
lodstats/stats/OrderedDict.py
lodstats/stats/Owl.py
lodstats/stats/ParsedVocabulary.py
lodstats/stats/Properties.py
lodstats/stats/PropertiesPerEntity.py
lodstats/stats/PropertyHierarchy.py
lodstats/stats/RDFSchema.py
lodstats/stats/RDFStatInterface.py
lodstats/stats/RDFSyntax.py
lodstats/stats/StringLength.py
lodstats/stats/Vocabularies.py
lodstats/stats/__init__.py
lodstats/stats/basics.py
lodstats/stats/distincthelper.py
lodstats/util/__init__.py
lodstats/util/format.py
lodstats/util/namespace.py
scripts/lodstats